secblast/__init__.py
secblast/async_client.py
secblast/client.py
secblast/exceptions.py
secblast/py.typed
secblast/endpoints/__init__.py
secblast/endpoints/documents.py
secblast/endpoints/entities.py
secblast/endpoints/filings.py
secblast/endpoints/financials.py
secblast/endpoints/search.py
secblast/models/__init__.py
secblast/models/entity.py
secblast/models/filing.py
secblast/models/financials.py
secblast/models/search.py
secblast-0.1.8.dist-info/METADATA
secblast-0.1.8.dist-info/WHEEL
secblast-0.1.8.dist-info/licenses/LICENSE
secblast-0.1.8.dist-info/RECORD
